menorah/__init__.py
menorah/confluence.py
menorah/confluencefactory.py
menorah/menorah.py
menorah/modelrunner.py
menorah/nupic_output.py
menorah/riverstream.py
menorah/swarmrunner.py
menorah/swarmtemplate.py
menorah/version.py
menorah-0.1.1.dist-info/DESCRIPTION.rst
menorah-0.1.1.dist-info/METADATA
menorah-0.1.1.dist-info/metadata.json
menorah-0.1.1.dist-info/RECORD
menorah-0.1.1.dist-info/top_level.txt
menorah-0.1.1.dist-info/WHEEL
