Metadata-Version: 2.0
Name: menorah
Version: 0.1.1
Summary: Converges many River View Streams into a NuPIC HTM model
Home-page: https://github.com/nupic-community/menorah
Author: Matthew Taylor
Author-email: matt@numenta.org
License: AGPL
Download-URL: https://github.com/nupic-community/menorah/archive/0.1.1.zip
Keywords: river,view,client,htm,nupic
Platform: UNKNOWN
Classifier: Development Status :: 5 - Production/Stable
Classifier: Environment :: Console
Classifier: Intended Audience :: Developers
Classifier: License :: OSI Approved :: GNU Affero General Public License v3 or later (AGPLv3+)
Classifier: Natural Language :: English
Classifier: Operating System :: OS Independent
Classifier: Programming Language :: Python
Requires-Dist: riverpy (==0.1.1)
